gcwd/__init__.py
gcwd/gcwd.py
gcwd/settings.py
gcwd-1.0.0.dist-info/LICENSE.txt
gcwd-1.0.0.dist-info/METADATA
gcwd-1.0.0.dist-info/WHEEL
gcwd-1.0.0.dist-info/entry_points.txt
gcwd-1.0.0.dist-info/top_level.txt
gcwd-1.0.0.dist-info/RECORD
