Metadata-Version: 2.1
Name: gcwd
Version: 1.0.0
Summary: Get connected wi-fi data easily.
Home-page: https://github.com/RaghavGohil/GCWD
Author: RaghavGohil
Author-email: raghavgohil2004@gmail.com
License: MIT LICENSE
Keywords: Get connected wi-fi data easily
Platform: UNKNOWN
Classifier: Development Status :: 1 - Planning
Classifier: License :: OSI Approved :: MIT License
Classifier: Operating System :: Microsoft
Requires-Python: >=3.0
Requires-Dist: regex (>=2022.3.15)
Requires-Dist: readme-renderer (>=21.0)
